jupyter_tigervnc_novnc_proxy/__init__.py
jupyter_tigervnc_novnc_proxy/app-icon.svg
jupyter_tigervnc_novnc_proxy/hooks.py
jupyter_tigervnc_novnc_proxy/vnc.sh
jupyter_tigervnc_novnc_proxy/extras/start-vnc-server-fg.sh
jupyter_tigervnc_novnc_proxy/extras/start-vnc-server.sh
jupyter_tigervnc_novnc_proxy/extras/supervisor/supervisor.conf
jupyter_tigervnc_novnc_proxy/extras/supervisor/conf.d/10-vncserver.conf
jupyter_tigervnc_novnc_proxy/extras/supervisor/conf.d/20-novncproxy.conf
jupyter_tigervnc_novnc_proxy/novnc/AUTHORS
jupyter_tigervnc_novnc_proxy/novnc/LICENSE.txt
jupyter_tigervnc_novnc_proxy/novnc/README.md
jupyter_tigervnc_novnc_proxy/novnc/defaults.json
jupyter_tigervnc_novnc_proxy/novnc/eslint.config.mjs
jupyter_tigervnc_novnc_proxy/novnc/karma.conf.js
jupyter_tigervnc_novnc_proxy/novnc/mandatory.json
jupyter_tigervnc_novnc_proxy/novnc/package.json
jupyter_tigervnc_novnc_proxy/novnc/vnc.html
jupyter_tigervnc_novnc_proxy/novnc/vnc_lite.html
jupyter_tigervnc_novnc_proxy/novnc/app/error-handler.js
jupyter_tigervnc_novnc_proxy/novnc/app/localization.js
jupyter_tigervnc_novnc_proxy/novnc/app/ui.js
jupyter_tigervnc_novnc_proxy/novnc/app/webutil.js
jupyter_tigervnc_novnc_proxy/novnc/app/images/alt.svg
jupyter_tigervnc_novnc_proxy/novnc/app/images/clipboard.svg
jupyter_tigervnc_novnc_proxy/novnc/app/images/connect.svg
jupyter_tigervnc_novnc_proxy/novnc/app/images/ctrl.svg
jupyter_tigervnc_novnc_proxy/novnc/app/images/ctrlaltdel.svg
jupyter_tigervnc_novnc_proxy/novnc/app/images/disconnect.svg
jupyter_tigervnc_novnc_proxy/novnc/app/images/drag.svg
jupyter_tigervnc_novnc_proxy/novnc/app/images/error.svg
jupyter_tigervnc_novnc_proxy/novnc/app/images/esc.svg
jupyter_tigervnc_novnc_proxy/novnc/app/images/expander.svg
jupyter_tigervnc_novnc_proxy/novnc/app/images/fullscreen.svg
jupyter_tigervnc_novnc_proxy/novnc/app/images/handle.svg
jupyter_tigervnc_novnc_proxy/novnc/app/images/handle_bg.svg
jupyter_tigervnc_novnc_proxy/novnc/app/images/info.svg
jupyter_tigervnc_novnc_proxy-1.0.1.dist-info/METADATA
jupyter_tigervnc_novnc_proxy-1.0.1.dist-info/WHEEL
jupyter_tigervnc_novnc_proxy-1.0.1.dist-info/entry_points.txt
jupyter_tigervnc_novnc_proxy-1.0.1.dist-info/licenses/LICENSE.md
jupyter_tigervnc_novnc_proxy-1.0.1.dist-info/RECORD
