Metadata-Version: 2.4
Name: jupyter-tigervnc-novnc-proxy
Version: 1.0.1
Summary: Jupyter server proxy for NOVNC
Project-URL: Homepage, https://github.com/huntdatacenter/jupyter-tigervnc-novnc-proxy
Author-email: Matus Kosut <matus.kosut@ntnu.no>, Jakub Hudak <jakub.hudak@ntnu.no>
License: MIT License
License-File: LICENSE.md
Keywords: Jupyter Proxy,Jupyter Server Proxy,JupyterLab
Classifier: Framework :: Jupyter
Classifier: Framework :: Jupyter :: JupyterLab
Classifier: Intended Audience :: Developers
Classifier: License :: OSI Approved :: MIT License
Classifier: Natural Language :: English
Classifier: Programming Language :: Python :: 3.8
Classifier: Programming Language :: Python :: 3.9
Classifier: Programming Language :: Python :: 3.10
Classifier: Programming Language :: Python :: 3.11
Classifier: Programming Language :: Python :: 3.12
Classifier: Programming Language :: Python :: 3.13
Classifier: Programming Language :: Python :: 3.14
Requires-Python: >=3.8
Requires-Dist: jupyter-server-proxy
Requires-Dist: supervisor
Requires-Dist: websockify
Provides-Extra: dev
Requires-Dist: black; extra == 'dev'
Requires-Dist: pytest; extra == 'dev'
Requires-Dist: pytest-cov; extra == 'dev'
Requires-Dist: ruamel-yaml; extra == 'dev'
